centercitypcs_utils/__init__.py
centercitypcs_utils-0.2.6.dist-info/LICENSE
centercitypcs_utils-0.2.6.dist-info/METADATA
centercitypcs_utils-0.2.6.dist-info/WHEEL
centercitypcs_utils-0.2.6.dist-info/RECORD
